cdk_cloudwatch_alarm_chatbot/__init__.py
cdk_cloudwatch_alarm_chatbot/py.typed
cdk_cloudwatch_alarm_chatbot/_jsii/__init__.py
cdk_cloudwatch_alarm_chatbot/_jsii/cdk-cloudwatch-alarm-chatbot@1.0.33.jsii.tgz
cdk_cloudwatch_alarm_chatbot-1.0.33.dist-info/LICENSE
cdk_cloudwatch_alarm_chatbot-1.0.33.dist-info/METADATA
cdk_cloudwatch_alarm_chatbot-1.0.33.dist-info/WHEEL
cdk_cloudwatch_alarm_chatbot-1.0.33.dist-info/top_level.txt
cdk_cloudwatch_alarm_chatbot-1.0.33.dist-info/RECORD
